label_location_local/LabelConstants.py
label_location_local/LabelLocation.py
label_location_local/__init__.py
label_location_local-0.0.13.dist-info/METADATA
label_location_local-0.0.13.dist-info/WHEEL
label_location_local-0.0.13.dist-info/top_level.txt
label_location_local-0.0.13.dist-info/RECORD
