Metadata-Version: 2.1
Name: label-location-local
Version: 0.0.13
Summary: PyPI Package for Circles label-location-local Python
Home-page: https://github.com/circles-zone/label-location-local-python-package
Author: Circles
Author-email: info@circlez.ai
Classifier: Programming Language :: Python :: 3
Classifier: License :: Other/Proprietary License
Classifier: Operating System :: OS Independent
Requires-Dist: logger-local >=0.0.135
Requires-Dist: database-mysql-local >=0.0.290
